criminal_dance/__init__.py
criminal_dance/cards/__init__.py
criminal_dance/cards/accomplice.py
criminal_dance/cards/cert.py
criminal_dance/cards/criminal.py
criminal_dance/cards/detect.py
criminal_dance/cards/dog.py
criminal_dance/cards/exchange.py
criminal_dance/cards/first.py
criminal_dance/cards/police.py
criminal_dance/cards/readme.md
criminal_dance/cards/round_give.py
criminal_dance/cards/rumor.py
criminal_dance/cards/simple.py
criminal_dance/cards/watch.py
criminal_dance/cat.py
criminal_dance/config.py
criminal_dance/info.py
criminal_dance/model.py
criminal_dance/room.py
criminal_dance/utils.py
criminal_dance-0.2.0.dist-info/LICENSE
criminal_dance-0.2.0.dist-info/METADATA
criminal_dance-0.2.0.dist-info/WHEEL
criminal_dance-0.2.0.dist-info/RECORD
