Metadata-Version: 2.1
Name: criminal-dance
Version: 0.2.0
Summary: 犯人在跳舞
Home-page: https://github.com/bridgeL/criminal_dance
License: MIT
Author: Su
Author-email: wxlxy316@163.com
Requires-Python: >=3.10,<4.0
Classifier: License :: OSI Approved :: MIT License
Classifier: Programming Language :: Python :: 3
Classifier: Programming Language :: Python :: 3.10
Classifier: Programming Language :: Python :: 3.11
Requires-Dist: ayaka (>=0.0.4.0,<0.0.5.0)
Project-URL: Repository, https://github.com/bridgeL/criminal_dance
